{
  "__data_type": "UTC ",
  "Appearance_Type": {
    "type": "word",
    "value": 1808
  },
  "BodyBag": {
    "type": "byte",
    "value": 0
  },
  "Cha": {
    "type": "byte",
    "value": 14
  },
  "ChallengeRating": {
    "type": "float",
    "value": 80.0
  },
  "ClassList": {
    "type": "list",
    "value": [
      {
        "__struct_id": 2,
        "Class": {
          "type": "int",
          "value": 4
        },
        "ClassLevel": {
          "type": "short",
          "value": 30
        }
      }
    ]
  },
  "Comment": {
    "type": "cexostring",
    "value": ""
  },
  "Con": {
    "type": "byte",
    "value": 20
  },
  "Conversation": {
    "type": "resref",
    "value": ""
  },
  "CRAdjust": {
    "type": "int",
    "value": 17
  },
  "CurrentHitPoints": {
    "type": "short",
    "value": 320
  },
  "DecayTime": {
    "type": "dword",
    "value": 5000
  },
  "Deity": {
    "type": "cexostring",
    "value": ""
  },
  "Description": {
    "id": 12793,
    "type": "cexolocstring",
    "value": {}
  },
  "Dex": {
    "type": "byte",
    "value": 14
  },
  "Disarmable": {
    "type": "byte",
    "value": 1
  },
  "Equip_ItemList": {
    "type": "list",
    "value": [
      {
        "__struct_id": 4,
        "EquippedRes": {
          "type": "resref",
          "value": "it_mboots006"
        }
      },
      {
        "__struct_id": 8,
        "EquippedRes": {
          "type": "resref",
          "value": "it_mbracer014"
        }
      },
      {
        "__struct_id": 16,
        "EquippedRes": {
          "type": "resref",
          "value": "wswmbs006"
        }
      },
      {
        "__struct_id": 512,
        "EquippedRes": {
          "type": "resref",
          "value": "it_mneck023"
        }
      },
      {
        "__struct_id": 1024,
        "EquippedRes": {
          "type": "resref",
          "value": "it_mbelt003"
        }
      },
      {
        "__struct_id": 65536,
        "EquippedRes": {
          "type": "resref",
          "value": "nw_crewpvbt"
        }
      },
      {
        "__struct_id": 131072,
        "EquippedRes": {
          "type": "resref",
          "value": "nw_creitemvam"
        }
      }
    ]
  },
  "FactionID": {
    "type": "word",
    "value": 1
  },
  "FeatList": {
    "type": "list",
    "value": [
      {
        "__struct_id": 1,
        "Feat": {
          "type": "word",
          "value": 0
        }
      },
      {
        "__struct_id": 1,
        "Feat": {
          "type": "word",
          "value": 2
        }
      },
      {
        "__struct_id": 1,
        "Feat": {
          "type": "word",
          "value": 3
        }
      },
      {
        "__struct_id": 1,
        "Feat": {
          "type": "word",
          "value": 4
        }
      },
      {
        "__struct_id": 1,
        "Feat": {
          "type": "word",
          "value": 490
        }
      },
      {
        "__struct_id": 1,
        "Feat": {
          "type": "word",
          "value": 408
        }
      },
      {
        "__struct_id": 1,
        "Feat": {
          "type": "word",
          "value": 379
        }
      },
      {
        "__struct_id": 1,
        "Feat": {
          "type": "word",
          "value": 478
        }
      },
      {
        "__struct_id": 1,
        "Feat": {
          "type": "word",
          "value": 5
        }
      },
      {
        "__struct_id": 1,
        "Feat": {
          "type": "word",
          "value": 6
        }
      },
      {
        "__struct_id": 1,
        "Feat": {
          "type": "word",
          "value": 458
        }
      },
      {
        "__struct_id": 1,
        "Feat": {
          "type": "word",
          "value": 528
        }
      },
      {
        "__struct_id": 1,
        "Feat": {
          "type": "word",
          "value": 9
        }
      },
      {
        "__struct_id": 1,
        "Feat": {
          "type": "word",
          "value": 10
        }
      },
      {
        "__struct_id": 1,
        "Feat": {
          "type": "word",
          "value": 1001
        }
      },
      {
        "__struct_id": 1,
        "Feat": {
          "type": "word",
          "value": 856
        }
      },
      {
        "__struct_id": 1,
        "Feat": {
          "type": "word",
          "value": 966
        }
      },
      {
        "__struct_id": 1,
        "Feat": {
          "type": "word",
          "value": 583
        }
      },
      {
        "__struct_id": 1,
        "Feat": {
          "type": "word",
          "value": 584
        }
      },
      {
        "__struct_id": 1,
        "Feat": {
          "type": "word",
          "value": 585
        }
      },
      {
        "__struct_id": 1,
        "Feat": {
          "type": "word",
          "value": 592
        }
      },
      {
        "__struct_id": 1,
        "Feat": {
          "type": "word",
          "value": 652
        }
      },
      {
        "__struct_id": 1,
        "Feat": {
          "type": "word",
          "value": 690
        }
      },
      {
        "__struct_id": 1,
        "Feat": {
          "type": "word",
          "value": 267
        }
      },
      {
        "__struct_id": 1,
        "Feat": {
          "type": "word",
          "value": 249
        }
      },
      {
        "__struct_id": 1,
        "Feat": {
          "type": "word",
          "value": 250
        }
      },
      {
        "__struct_id": 1,
        "Feat": {
          "type": "word",
          "value": 391
        }
      },
      {
        "__struct_id": 1,
        "Feat": {
          "type": "word",
          "value": 14
        }
      },
      {
        "__struct_id": 1,
        "Feat": {
          "type": "word",
          "value": 822
        }
      },
      {
        "__struct_id": 1,
        "Feat": {
          "type": "word",
          "value": 1042
        }
      },
      {
        "__struct_id": 1,
        "Feat": {
          "type": "word",
          "value": 85
        }
      },
      {
        "__struct_id": 1,
        "Feat": {
          "type": "word",
          "value": 390
        }
      },
      {
        "__struct_id": 1,
        "Feat": {
          "type": "word",
          "value": 477
        }
      },
      {
        "__struct_id": 1,
        "Feat": {
          "type": "word",
          "value": 476
        }
      },
      {
        "__struct_id": 1,
        "Feat": {
          "type": "word",
          "value": 240
        }
      },
      {
        "__struct_id": 1,
        "Feat": {
          "type": "word",
          "value": 885
        }
      },
      {
        "__struct_id": 1,
        "Feat": {
          "type": "word",
          "value": 24
        }
      },
      {
        "__struct_id": 1,
        "Feat": {
          "type": "word",
          "value": 26
        }
      },
      {
        "__struct_id": 1,
        "Feat": {
          "type": "word",
          "value": 224
        }
      },
      {
        "__struct_id": 1,
        "Feat": {
          "type": "word",
          "value": 742
        }
      },
      {
        "__struct_id": 1,
        "Feat": {
          "type": "word",
          "value": 27
        }
      },
      {
        "__struct_id": 1,
        "Feat": {
          "type": "word",
          "value": 28
        }
      },
      {
        "__struct_id": 1,
        "Feat": {
          "type": "word",
          "value": 258
        }
      },
      {
        "__struct_id": 1,
        "Feat": {
          "type": "word",
          "value": 31
        }
      },
      {
        "__struct_id": 1,
        "Feat": {
          "type": "word",
          "value": 32
        }
      },
      {
        "__struct_id": 1,
        "Feat": {
          "type": "word",
          "value": 39
        }
      },
      {
        "__struct_id": 1,
        "Feat": {
          "type": "word",
          "value": 989
        }
      },
      {
        "__struct_id": 1,
        "Feat": {
          "type": "word",
          "value": 988
        }
      },
      {
        "__struct_id": 1,
        "Feat": {
          "type": "word",
          "value": 894
        }
      },
      {
        "__struct_id": 1,
        "Feat": {
          "type": "word",
          "value": 40
        }
      },
      {
        "__struct_id": 1,
        "Feat": {
          "type": "word",
          "value": 123
        }
      },
      {
        "__struct_id": 1,
        "Feat": {
          "type": "word",
          "value": 101
        }
      },
      {
        "__struct_id": 1,
        "Feat": {
          "type": "word",
          "value": 940
        }
      },
      {
        "__struct_id": 1,
        "Feat": {
          "type": "word",
          "value": 289
        }
      },
      {
        "__struct_id": 1,
        "Feat": {
          "type": "word",
          "value": 44
        }
      },
      {
        "__struct_id": 1,
        "Feat": {
          "type": "word",
          "value": 45
        }
      },
      {
        "__struct_id": 1,
        "Feat": {
          "type": "word",
          "value": 46
        }
      },
      {
        "__struct_id": 1,
        "Feat": {
          "type": "word",
          "value": 161
        }
      }
    ]
  },
  "FirstName": {
    "id": 12794,
    "type": "cexolocstring",
    "value": {
      "0": "Vampire Warrior, Flying",
      "4": "Fliegender Tod"
    }
  },
  "fortbonus": {
    "type": "short",
    "value": 10
  },
  "Gender": {
    "type": "byte",
    "value": 0
  },
  "GoodEvil": {
    "type": "byte",
    "value": 0
  },
  "HitPoints": {
    "type": "short",
    "value": 320
  },
  "Int": {
    "type": "byte",
    "value": 12
  },
  "Interruptable": {
    "type": "byte",
    "value": 1
  },
  "IsImmortal": {
    "type": "byte",
    "value": 0
  },
  "IsPC": {
    "type": "byte",
    "value": 0
  },
  "LastName": {
    "type": "cexolocstring",
    "value": {}
  },
  "LawfulChaotic": {
    "type": "byte",
    "value": 0
  },
  "Lootable": {
    "type": "byte",
    "value": 0
  },
  "MaxHitPoints": {
    "type": "short",
    "value": 500
  },
  "NaturalAC": {
    "type": "byte",
    "value": 30
  },
  "NoPermDeath": {
    "type": "byte",
    "value": 0
  },
  "PaletteID": {
    "type": "byte",
    "value": 69
  },
  "PerceptionRange": {
    "type": "byte",
    "value": 11
  },
  "Phenotype": {
    "type": "int",
    "value": 0
  },
  "Plot": {
    "type": "byte",
    "value": 0
  },
  "PortraitId": {
    "type": "word",
    "value": 3323
  },
  "Race": {
    "type": "byte",
    "value": 24
  },
  "refbonus": {
    "type": "short",
    "value": 20
  },
  "ScriptAttacked": {
    "type": "resref",
    "value": "nw_c2_default5"
  },
  "ScriptDamaged": {
    "type": "resref",
    "value": "nw_c2_default6"
  },
  "ScriptDeath": {
    "type": "resref",
    "value": "nw_c2_default7"
  },
  "ScriptDialogue": {
    "type": "resref",
    "value": "nw_c2_default4"
  },
  "ScriptDisturbed": {
    "type": "resref",
    "value": "nw_c2_default8"
  },
  "ScriptEndRound": {
    "type": "resref",
    "value": "nw_c2_default3"
  },
  "ScriptHeartbeat": {
    "type": "resref",
    "value": "nw_c2_default1"
  },
  "ScriptOnBlocked": {
    "type": "resref",
    "value": "nw_c2_defaulte"
  },
  "ScriptOnNotice": {
    "type": "resref",
    "value": "nw_c2_default2"
  },
  "ScriptRested": {
    "type": "resref",
    "value": "nw_c2_defaulta"
  },
  "ScriptSpawn": {
    "type": "resref",
    "value": "nw_c2_default9"
  },
  "ScriptSpellAt": {
    "type": "resref",
    "value": "nw_c2_defaultb"
  },
  "ScriptUserDefine": {
    "type": "resref",
    "value": "nw_c2_defaultd"
  },
  "SkillList": {
    "type": "list",
    "value": [
      {
        "__struct_id": 0,
        "Rank": {
          "type": "byte",
          "value": 0
        }
      },
      {
        "__struct_id": 0,
        "Rank": {
          "type": "byte",
          "value": 0
        }
      },
      {
        "__struct_id": 0,
        "Rank": {
          "type": "byte",
          "value": 0
        }
      },
      {
        "__struct_id": 0,
        "Rank": {
          "type": "byte",
          "value": 14
        }
      },
      {
        "__struct_id": 0,
        "Rank": {
          "type": "byte",
          "value": 0
        }
      },
      {
        "__struct_id": 0,
        "Rank": {
          "type": "byte",
          "value": 8
        }
      },
      {
        "__struct_id": 0,
        "Rank": {
          "type": "byte",
          "value": 8
        }
      },
      {
        "__struct_id": 0,
        "Rank": {
          "type": "byte",
          "value": 0
        }
      },
      {
        "__struct_id": 0,
        "Rank": {
          "type": "byte",
          "value": 8
        }
      },
      {
        "__struct_id": 0,
        "Rank": {
          "type": "byte",
          "value": 0
        }
      },
      {
        "__struct_id": 0,
        "Rank": {
          "type": "byte",
          "value": 12
        }
      },
      {
        "__struct_id": 0,
        "Rank": {
          "type": "byte",
          "value": 0
        }
      },
      {
        "__struct_id": 0,
        "Rank": {
          "type": "byte",
          "value": 0
        }
      },
      {
        "__struct_id": 0,
        "Rank": {
          "type": "byte",
          "value": 0
        }
      },
      {
        "__struct_id": 0,
        "Rank": {
          "type": "byte",
          "value": 8
        }
      },
      {
        "__struct_id": 0,
        "Rank": {
          "type": "byte",
          "value": 0
        }
      },
      {
        "__struct_id": 0,
        "Rank": {
          "type": "byte",
          "value": 0
        }
      },
      {
        "__struct_id": 0,
        "Rank": {
          "type": "byte",
          "value": 8
        }
      },
      {
        "__struct_id": 0,
        "Rank": {
          "type": "byte",
          "value": 0
        }
      },
      {
        "__struct_id": 0,
        "Rank": {
          "type": "byte",
          "value": 0
        }
      },
      {
        "__struct_id": 0,
        "Rank": {
          "type": "byte",
          "value": 0
        }
      },
      {
        "__struct_id": 0,
        "Rank": {
          "type": "byte",
          "value": 0
        }
      },
      {
        "__struct_id": 0,
        "Rank": {
          "type": "byte",
          "value": 0
        }
      },
      {
        "__struct_id": 0,
        "Rank": {
          "type": "byte",
          "value": 0
        }
      },
      {
        "__struct_id": 0,
        "Rank": {
          "type": "byte",
          "value": 0
        }
      },
      {
        "__struct_id": 0,
        "Rank": {
          "type": "byte",
          "value": 0
        }
      },
      {
        "__struct_id": 0,
        "Rank": {
          "type": "byte",
          "value": 0
        }
      },
      {
        "__struct_id": 0,
        "Rank": {
          "type": "byte",
          "value": 0
        }
      }
    ]
  },
  "SoundSetFile": {
    "type": "word",
    "value": 96
  },
  "SpecAbilityList": {
    "type": "list",
    "value": [
      {
        "__struct_id": 4,
        "Spell": {
          "type": "word",
          "value": 198
        },
        "SpellCasterLevel": {
          "type": "byte",
          "value": 0
        },
        "SpellFlags": {
          "type": "byte",
          "value": 1
        }
      }
    ]
  },
  "StartingPackage": {
    "type": "byte",
    "value": 4
  },
  "Str": {
    "type": "byte",
    "value": 28
  },
  "Subrace": {
    "type": "cexostring",
    "value": ""
  },
  "Tag": {
    "type": "cexostring",
    "value": "que_vampfliegtod"
  },
  "Tail_New": {
    "type": "dword",
    "value": 205
  },
  "TemplateList": {
    "type": "list",
    "value": []
  },
  "TemplateResRef": {
    "type": "resref",
    "value": "que_vampfliegtod"
  },
  "WalkRate": {
    "type": "int",
    "value": 7
  },
  "willbonus": {
    "type": "short",
    "value": 10
  },
  "Wings_New": {
    "type": "dword",
    "value": 45
  },
  "Wis": {
    "type": "byte",
    "value": 14
  }
}
