{
  "__data_type": "DLG ",
  "DelayEntry": {
    "type": "dword",
    "value": 0
  },
  "DelayReply": {
    "type": "dword",
    "value": 0
  },
  "EndConverAbort": {
    "type": "resref",
    "value": "nw_walk_wp"
  },
  "EndConversation": {
    "type": "resref",
    "value": "nw_walk_wp"
  },
  "EntryList": {
    "type": "list",
    "value": [
      {
        "__struct_id": 0,
        "Animation": {
          "type": "dword",
          "value": 0
        },
        "AnimLoop": {
          "type": "byte",
          "value": 1
        },
        "Comment": {
          "type": "cexostring",
          "value": ""
        },
        "Delay": {
          "type": "dword",
          "value": 4294967295
        },
        "Quest": {
          "type": "cexostring",
          "value": ""
        },
        "RepliesList": {
          "type": "list",
          "value": []
        },
        "Script": {
          "type": "resref",
          "value": ""
        },
        "Sound": {
          "type": "resref",
          "value": ""
        },
        "Speaker": {
          "type": "cexostring",
          "value": ""
        },
        "Text": {
          "type": "cexolocstring",
          "value": {
            "4": "*verengt den Blick und faucht dich mit gesenkter Stimme an* Hier ist mein Gebiet und wenn du nicht sofort verschwindest lernst du das Hafenbecken kennen!"
          }
        }
      },
      {
        "__struct_id": 1,
        "Animation": {
          "type": "dword",
          "value": 0
        },
        "AnimLoop": {
          "type": "byte",
          "value": 1
        },
        "Comment": {
          "type": "cexostring",
          "value": ""
        },
        "Delay": {
          "type": "dword",
          "value": 4294967295
        },
        "Quest": {
          "type": "cexostring",
          "value": ""
        },
        "RepliesList": {
          "type": "list",
          "value": []
        },
        "Script": {
          "type": "resref",
          "value": ""
        },
        "Sound": {
          "type": "resref",
          "value": ""
        },
        "Speaker": {
          "type": "cexostring",
          "value": ""
        },
        "Text": {
          "type": "cexolocstring",
          "value": {
            "4": "*mit rauchig gehauchter Stimme und einem laziven Augenaufschlag* Wollen wir uns ein wenig die Zeit vertreiben? *ihre vollen Lippen zu einem Lächeln bewegt*"
          }
        }
      }
    ]
  },
  "NumWords": {
    "type": "dword",
    "value": 48
  },
  "PreventZoomIn": {
    "type": "byte",
    "value": 0
  },
  "ReplyList": {
    "type": "list",
    "value": []
  },
  "StartingList": {
    "type": "list",
    "value": [
      {
        "__struct_id": 0,
        "Active": {
          "type": "resref",
          "value": "gesp_julia_m"
        },
        "Index": {
          "type": "dword",
          "value": 1
        }
      },
      {
        "__struct_id": 1,
        "Active": {
          "type": "resref",
          "value": "gesp_julia_w"
        },
        "Index": {
          "type": "dword",
          "value": 0
        }
      }
    ]
  }
}
